LICENSE
MANIFEST.in
README.md
requirements.txt
setup.py
line_chain/__init__.py
line_chain/__version__.py
line_chain/line_chain.py
line_chain.egg-info/PKG-INFO
line_chain.egg-info/SOURCES.txt
line_chain.egg-info/dependency_links.txt
line_chain.egg-info/requires.txt
line_chain.egg-info/top_level.txt
line_chain/configs/__init__.py
line_chain/configs/build/__init__.py
line_chain/configs/build/line_chain_config.py
line_chain/schema/line_chain_config.json