Metadata-Version: 2.1
Name: line-chain
Version: 0.0.2.post1
Summary: Value Scheduler based on Progress
Home-page: https://github.com/FebruaryBreeze/line-chain
Author: SF-Zhou
Author-email: sfzhou.scut@gmail.com
License: MIT
Keywords: Scheduler Progress
Platform: UNKNOWN
Requires-Python: >=3.6.0
